rtdce/__init__.py
rtdce/enforce.py
rtdce/exceptions.py
rtdce-1.0.1.dist-info/LICENSE
rtdce-1.0.1.dist-info/METADATA
rtdce-1.0.1.dist-info/WHEEL
rtdce-1.0.1.dist-info/top_level.txt
rtdce-1.0.1.dist-info/RECORD
